d8s_timezones/__init__.py
d8s_timezones/democritus_timezones.py
d8s_timezones/democritus_timezones_temp_utils.py
tests/__init__.py
tests/test_democritus_timezones.py
d8s_timezones-0.5.0.dist-info/COPYING
d8s_timezones-0.5.0.dist-info/COPYING.LESSER
d8s_timezones-0.5.0.dist-info/METADATA
d8s_timezones-0.5.0.dist-info/WHEEL
d8s_timezones-0.5.0.dist-info/top_level.txt
d8s_timezones-0.5.0.dist-info/zip-safe
d8s_timezones-0.5.0.dist-info/RECORD
